swbuilder/__init__.py
swbuilder/__main__.py
swbuilder/_version.py
swbuilder/builds.py
swbuilder/cli.py
swbuilder/errors.py
swbuilder/imagedefs.py
swbuilder/staging.py
swbuilder/step.py
swbuilder/utils.py
swbuilder-1.0.1.6.dist-info/METADATA
swbuilder-1.0.1.6.dist-info/WHEEL
swbuilder-1.0.1.6.dist-info/entry_points.txt
swbuilder-1.0.1.6.dist-info/top_level.txt
swbuilder-1.0.1.6.dist-info/RECORD
