Metadata-Version: 2.1
Name: swbuilder
Version: 1.0.1.6
Summary: suwell images build tools
Home-page: http://www.atoml.com
Author: Aaron Virshup
Author-email: caijun@atoml.com
License: Apache 2.0
Requires-Python: >=3.6
Requires-Dist: termcolor
Requires-Dist: docker (>=4)
Requires-Dist: pyyaml (>=5)
Requires-Dist: atoml-utility (>=2.3.4.10)
